{
    "Metric": {
        "Id": "PerdidasEner",
        "Name": "Perdidas de Energía por Sistema",
        "StartDate": "2023-03-04T00:00:00",
        "EndDate": "2023-04-03T00:00:00"
    },
    "Items": [
        {
            "Date": "2023-03-04",
            "HourlyEntities": [
                {
                    "Id": "Sistema",
                    "Values": {
                        "code": "Sistema",
                        "Hour01": "170539.13000",
                        "Hour02": "170848.06000",
                        "Hour03": "169038.80000",
                        "Hour04": "151514.47000",
                        "Hour05": "147824.90000",
                        "Hour06": "150623.19000",
                        "Hour07": "134659.40000",
                        "Hour08": "119682.73000",
                        "Hour09": "102671.59000",
                        "Hour10": "105259.02000",
                        "Hour11": "104888.92000",
                        "Hour12": "111031.13000",
                        "Hour13": "117015.79000",
                        "Hour14": "117318.06000",
                        "Hour15": "121438.03000",
                        "Hour16": "129797.63000",
                        "Hour17": "152651.08000",
                        "Hour18": "167162.81000",
                        "Hour19": "183636.87000",
                        "Hour20": "188676.84000",
                        "Hour21": "182015.59000",
                        "Hour22": "180466.62000",
                        "Hour23": "176890.10000",
                        "Hour24": "167484.67000"
                    }
                }
            ]
        },
        {
            "Date": "2023-03-05",
            "HourlyEntities": [
                {
                    "Id": "Sistema",
                    "Values": {
                        "code": "Sistema",
                        "Hour01": "151234.96000",
                        "Hour02": "143004.36000",
                        "Hour03": "145867.56000",
                        "Hour04": "140824.23000",
                        "Hour05": "139906.76000",
                        "Hour06": "138110.62000",
                        "Hour07": "124405.03000",
                        "Hour08": "121431.56000",
                        "Hour09": "113394.90000",
                        "Hour10": "117102.56000",
                        "Hour11": "112414.40000",
                        "Hour12": "114589.54000",
                        "Hour13": "112873.01000",
                        "Hour14": "116784.99000",
                        "Hour15": "117950.10000",
                        "Hour16": "123873.31000",
                        "Hour17": "122640.40000",
                        "Hour18": "115844.45000",
                        "Hour19": "121852.75000",
                        "Hour20": "133434.06000",
                        "Hour21": "135469.71000",
                        "Hour22": "139721.56000",
                        "Hour23": "141937.22000",
                        "Hour24": "135507.35000"
                    }
                }
            ]
        },
        {
            "Date": "2023-03-06",
            "HourlyEntities": [
                {
                    "Id": "Sistema",
                    "Values": {
                        "code": "Sistema",
                        "Hour01": "145784.14000",
                        "Hour02": "145857.73000",
                        "Hour03": "147060.52000",
                        "Hour04": "136641.20000",
                        "Hour05": "121043.37000",
                        "Hour06": "123576.52000",
                        "Hour07": "125056.06000",
                        "Hour08": "119807.45000",
                        "Hour09": "122231.97000",
                        "Hour10": "121227.10000",
                        "Hour11": "129773.68000",
                        "Hour12": "138443.30000",
                        "Hour13": "147659.43000",
                        "Hour14": "143732.32000",
                        "Hour15": "166717.40000",
                        "Hour16": "165877.24000",
                        "Hour17": "158269.32000",
                        "Hour18": "153677.14000",
                        "Hour19": "141883.38000",
                        "Hour20": "157793.86000",
                        "Hour21": "155900.49000",
                        "Hour22": "158336.85000",
                        "Hour23": "143085.68000",
                        "Hour24": "132710.14000"
                    }
                }
            ]
        },
        {
            "Date": "2023-03-07",
            "HourlyEntities": [
                {
                    "Id": "Sistema",
                    "Values": {
                        "code": "Sistema",
                        "Hour01": "149126.79000",
                        "Hour02": "168424.02000",
                        "Hour03": "160432.29000",
                        "Hour04": "152416.28000",
                        "Hour05": "133649.48000",
                        "Hour06": "142180.86000",
                        "Hour07": "129947.07000",
                        "Hour08": "123012.69000",
                        "Hour09": "123643.25000",
                        "Hour10": "122588.00000",
                        "Hour11": "125187.76000",
                        "Hour12": "135414.82000",
                        "Hour13": "139370.02000",
                        "Hour14": "149041.75000",
                        "Hour15": "144864.09000",
                        "Hour16": "150997.99000",
                        "Hour17": "150500.19000",
                        "Hour18": "150923.01000",
                        "Hour19": "131893.09000",
                        "Hour20": "146596.35000",
                        "Hour21": "142672.43000",
                        "Hour22": "167831.11000",
                        "Hour23": "167180.85000",
                        "Hour24": "144361.61000"
                    }
                }
            ]
        },
        {
            "Date": "2023-03-08",
            "HourlyEntities": [
                {
                    "Id": "Sistema",
                    "Values": {
                        "code": "Sistema",
                        "Hour01": "125810.68000",
                        "Hour02": "128741.55000",
                        "Hour03": "116179.04000",
                        "Hour04": "112250.79000",
                        "Hour05": "122501.52000",
                        "Hour06": "118836.09000",
                        "Hour07": "105137.90000",
                        "Hour08": "100393.06000",
                        "Hour09": "104614.16000",
                        "Hour10": "118983.11000",
                        "Hour11": "106178.90000",
                        "Hour12": "125263.36000",
                        "Hour13": "113092.68000",
                        "Hour14": "127866.79000",
                        "Hour15": "141259.47000",
                        "Hour16": "153140.28000",
                        "Hour17": "153941.11000",
                        "Hour18": "127991.87000",
                        "Hour19": "132470.50000",
                        "Hour20": "132556.14000",
                        "Hour21": "137026.81000",
                        "Hour22": "142895.10000",
                        "Hour23": "131350.24000",
                        "Hour24": "125406.91000"
                    }
                }
            ]
        },
        {
            "Date": "2023-03-09",
            "HourlyEntities": [
                {
                    "Id": "Sistema",
                    "Values": {
                        "code": "Sistema",
                        "Hour01": "114288.51000",
                        "Hour02": "133124.28000",
                        "Hour03": "129806.37000",
                        "Hour04": "124665.42000",
                        "Hour05": "119639.17000",
                        "Hour06": "133784.73000",
                        "Hour07": "131612.60000",
                        "Hour08": "136890.72000",
                        "Hour09": "146259.73000",
                        "Hour10": "134279.63000",
                        "Hour11": "133993.73000",
                        "Hour12": "135410.03000",
                        "Hour13": "131534.84000",
                        "Hour14": "128128.52000",
                        "Hour15": "137567.90000",
                        "Hour16": "140160.10000",
                        "Hour17": "140007.71000",
                        "Hour18": "135001.63000",
                        "Hour19": "139335.02000",
                        "Hour20": "146558.06000",
                        "Hour21": "139238.55000",
                        "Hour22": "137825.32000",
                        "Hour23": "120316.81000",
                        "Hour24": "119850.09000"
                    }
                }
            ]
        },
        {
            "Date": "2023-03-10",
            "HourlyEntities": [
                {
                    "Id": "Sistema",
                    "Values": {
                        "code": "Sistema",
                        "Hour01": "136401.37000",
                        "Hour02": "130224.42000",
                        "Hour03": "125774.89000",
                        "Hour04": "121928.87000",
                        "Hour05": "117675.36000",
                        "Hour06": "123081.63000",
                        "Hour07": "119795.11000",
                        "Hour08": "109648.96000",
                        "Hour09": "115592.95000",
                        "Hour10": "120252.69000",
                        "Hour11": "123979.87000",
                        "Hour12": "142507.21000",
                        "Hour13": "146467.41000",
                        "Hour14": "149866.07000",
                        "Hour15": "154567.55000",
                        "Hour16": "153520.52000",
                        "Hour17": "152520.36000",
                        "Hour18": "145600.67000",
                        "Hour19": "153884.80000",
                        "Hour20": "166789.66000",
                        "Hour21": "168606.27000",
                        "Hour22": "163751.16000",
                        "Hour23": "148433.23000",
                        "Hour24": "139003.79000"
                    }
                }
            ]
        },
        {
            "Date": "2023-03-11",
            "HourlyEntities": [
                {
                    "Id": "Sistema",
                    "Values": {
                        "code": "Sistema",
                        "Hour01": "163122.67000",
                        "Hour02": "166594.88000",
                        "Hour03": "166351.53000",
                        "Hour04": "147560.01000",
                        "Hour05": "148730.09000",
                        "Hour06": "137527.35000",
                        "Hour07": "129174.74000",
                        "Hour08": "141809.28000",
                        "Hour09": "126634.05000",
                        "Hour10": "125850.96000",
                        "Hour11": "127742.53000",
                        "Hour12": "122944.01000",
                        "Hour13": "124357.26000",
                        "Hour14": "129423.02000",
                        "Hour15": "127873.44000",
                        "Hour16": "131248.90000",
                        "Hour17": "137850.94000",
                        "Hour18": "140892.25000",
                        "Hour19": "154434.90000",
                        "Hour20": "142621.26000",
                        "Hour21": "130137.08000",
                        "Hour22": "135936.85000",
                        "Hour23": "149830.01000",
                        "Hour24": "164314.72000"
                    }
                }
            ]
        },
        {
            "Date": "2023-03-12",
            "HourlyEntities": [
                {
                    "Id": "Sistema",
                    "Values": {
                        "code": "Sistema",
                        "Hour01": "155949.45000",
                        "Hour02": "156006.76000",
                        "Hour03": "163565.44000",
                        "Hour04": "161349.33000",
                        "Hour05": "161395.58000",
                        "Hour06": "158602.70000",
                        "Hour07": "139939.97000",
                        "Hour08": "135955.50000",
                        "Hour09": "135886.95000",
                        "Hour10": "136895.76000",
                        "Hour11": "136873.86000",
                        "Hour12": "144540.33000",
                        "Hour13": "152820.60000",
                        "Hour14": "160252.63000",
                        "Hour15": "152979.28000",
                        "Hour16": "153428.17000",
                        "Hour17": "156727.17000",
                        "Hour18": "164134.58000",
                        "Hour19": "164179.20000",
                        "Hour20": "165651.16000",
                        "Hour21": "167945.18000",
                        "Hour22": "168554.90000",
                        "Hour23": "179992.92000",
                        "Hour24": "178472.25000"
                    }
                }
            ]
        },
        {
            "Date": "2023-03-13",
            "HourlyEntities": [
                {
                    "Id": "Sistema",
                    "Values": {
                        "code": "Sistema",
                        "Hour01": "161851.29000",
                        "Hour02": "158014.88000",
                        "Hour03": "164924.36000",
                        "Hour04": "163113.93000",
                        "Hour05": "154009.12000",
                        "Hour06": "150800.34000",
                        "Hour07": "141674.88000",
                        "Hour08": "141101.84000",
                        "Hour09": "140757.95000",
                        "Hour10": "141166.97000",
                        "Hour11": "146059.22000",
                        "Hour12": "156986.67000",
                        "Hour13": "148807.48000",
                        "Hour14": "147112.92000",
                        "Hour15": "151019.03000",
                        "Hour16": "152407.54000",
                        "Hour17": "160535.72000",
                        "Hour18": "158086.06000",
                        "Hour19": "156008.29000",
                        "Hour20": "162312.08000",
                        "Hour21": "159718.69000",
                        "Hour22": "153576.04000",
                        "Hour23": "143749.72000",
                        "Hour24": "140837.56000"
                    }
                }
            ]
        },
        {
            "Date": "2023-03-14",
            "HourlyEntities": [
                {
                    "Id": "Sistema",
                    "Values": {
                        "code": "Sistema",
                        "Hour01": "150546.75000",
                        "Hour02": "152328.43000",
                        "Hour03": "143724.26000",
                        "Hour04": "138313.87000",
                        "Hour05": "139701.02000",
                        "Hour06": "163378.08000",
                        "Hour07": "151237.72000",
                        "Hour08": "145030.10000",
                        "Hour09": "134948.05000",
                        "Hour10": "129868.83000",
                        "Hour11": "130128.81000",
                        "Hour12": "137000.66000",
                        "Hour13": "126244.84000",
                        "Hour14": "144004.51000",
                        "Hour15": "160591.72000",
                        "Hour16": "159484.84000",
                        "Hour17": "168559.91000",
                        "Hour18": "147912.73000",
                        "Hour19": "165946.60000",
                        "Hour20": "169351.71000",
                        "Hour21": "174959.23000",
                        "Hour22": "161898.31000",
                        "Hour23": "160594.03000",
                        "Hour24": "170874.64000"
                    }
                }
            ]
        },
        {
            "Date": "2023-03-15",
            "HourlyEntities": [
                {
                    "Id": "Sistema",
                    "Values": {
                        "code": "Sistema",
                        "Hour01": "167484.07000",
                        "Hour02": "161105.58000",
                        "Hour03": "149966.30000",
                        "Hour04": "147428.57000",
                        "Hour05": "149308.65000",
                        "Hour06": "161673.31000",
                        "Hour07": "160164.28000",
                        "Hour08": "168494.51000",
                        "Hour09": "182685.87000",
                        "Hour10": "173736.29000",
                        "Hour11": "141666.44000",
                        "Hour12": "136831.30000",
                        "Hour13": "143071.22000",
                        "Hour14": "153173.78000",
                        "Hour15": "155296.47000",
                        "Hour16": "146843.48000",
                        "Hour17": "164637.89000",
                        "Hour18": "147350.03000",
                        "Hour19": "145960.23000",
                        "Hour20": "150945.91000",
                        "Hour21": "154820.71000",
                        "Hour22": "153646.79000",
                        "Hour23": "158332.19000",
                        "Hour24": "164748.24000"
                    }
                }
            ]
        },
        {
            "Date": "2023-03-16",
            "HourlyEntities": [
                {
                    "Id": "Sistema",
                    "Values": {
                        "code": "Sistema",
                        "Hour01": "147016.56000",
                        "Hour02": "122992.40000",
                        "Hour03": "122164.67000",
                        "Hour04": "110965.63000",
                        "Hour05": "116470.67000",
                        "Hour06": "144044.37000",
                        "Hour07": "146503.89000",
                        "Hour08": "135160.22000",
                        "Hour09": "137939.42000",
                        "Hour10": "136673.73000",
                        "Hour11": "138339.96000",
                        "Hour12": "136168.38000",
                        "Hour13": "121712.11000",
                        "Hour14": "134330.58000",
                        "Hour15": "125687.82000",
                        "Hour16": "135377.75000",
                        "Hour17": "151373.90000",
                        "Hour18": "146737.24000",
                        "Hour19": "146019.77000",
                        "Hour20": "153111.97000",
                        "Hour21": "159507.86000",
                        "Hour22": "153798.50000",
                        "Hour23": "136856.18000",
                        "Hour24": "119660.55000"
                    }
                }
            ]
        },
        {
            "Date": "2023-03-17",
            "HourlyEntities": [
                {
                    "Id": "Sistema",
                    "Values": {
                        "code": "Sistema",
                        "Hour01": "102876.89000",
                        "Hour02": "95983.17000",
                        "Hour03": "101477.66000",
                        "Hour04": "92068.87000",
                        "Hour05": "110088.25000",
                        "Hour06": "125065.69000",
                        "Hour07": "103351.98000",
                        "Hour08": "94444.54000",
                        "Hour09": "91903.14000",
                        "Hour10": "98496.63000",
                        "Hour11": "118251.33000",
                        "Hour12": "137419.69000",
                        "Hour13": "131585.81000",
                        "Hour14": "130330.64000",
                        "Hour15": "134912.84000",
                        "Hour16": "146266.12000",
                        "Hour17": "141308.02000",
                        "Hour18": "139296.98000",
                        "Hour19": "139314.72000",
                        "Hour20": "158397.55000",
                        "Hour21": "150770.10000",
                        "Hour22": "148534.26000",
                        "Hour23": "139373.00000",
                        "Hour24": "137983.41000"
                    }
                }
            ]
        },
        {
            "Date": "2023-03-18",
            "HourlyEntities": [
                {
                    "Id": "Sistema",
                    "Values": {
                        "code": "Sistema",
                        "Hour01": "132272.06000",
                        "Hour02": "124570.19000",
                        "Hour03": "131563.00000",
                        "Hour04": "127519.74000",
                        "Hour05": "129282.03000",
                        "Hour06": "127266.09000",
                        "Hour07": "110095.17000",
                        "Hour08": "107819.81000",
                        "Hour09": "107022.58000",
                        "Hour10": "101934.87000",
                        "Hour11": "104427.43000",
                        "Hour12": "106880.59000",
                        "Hour13": "108320.76000",
                        "Hour14": "115698.82000",
                        "Hour15": "121458.88000",
                        "Hour16": "118382.85000",
                        "Hour17": "112547.87000",
                        "Hour18": "112594.56000",
                        "Hour19": "125285.87000",
                        "Hour20": "115990.13000",
                        "Hour21": "110160.28000",
                        "Hour22": "126787.80000",
                        "Hour23": "120668.18000",
                        "Hour24": "121631.89000"
                    }
                }
            ]
        },
        {
            "Date": "2023-03-19",
            "HourlyEntities": [
                {
                    "Id": "Sistema",
                    "Values": {
                        "code": "Sistema",
                        "Hour01": "117943.52000",
                        "Hour02": "123004.15000",
                        "Hour03": "124946.35000",
                        "Hour04": "114162.99000",
                        "Hour05": "117227.28000",
                        "Hour06": "119062.28000",
                        "Hour07": "108612.63000",
                        "Hour08": "99397.55000",
                        "Hour09": "103124.92000",
                        "Hour10": "102503.16000",
                        "Hour11": "106512.54000",
                        "Hour12": "107884.91000",
                        "Hour13": "98833.11000",
                        "Hour14": "107796.28000",
                        "Hour15": "100315.56000",
                        "Hour16": "110117.42000",
                        "Hour17": "108106.87000",
                        "Hour18": "102530.89000",
                        "Hour19": "104000.46000",
                        "Hour20": "115654.06000",
                        "Hour21": "121432.23000",
                        "Hour22": "126779.22000",
                        "Hour23": "123336.25000",
                        "Hour24": "162371.75000"
                    }
                }
            ]
        },
        {
            "Date": "2023-03-20",
            "HourlyEntities": [
                {
                    "Id": "Sistema",
                    "Values": {
                        "code": "Sistema",
                        "Hour01": "129416.10000",
                        "Hour02": "131472.17000",
                        "Hour03": "133165.81000",
                        "Hour04": "132587.99000",
                        "Hour05": "129375.15000",
                        "Hour06": "129459.10000",
                        "Hour07": "114322.68000",
                        "Hour08": "106312.09000",
                        "Hour09": "96489.68000",
                        "Hour10": "89871.74000",
                        "Hour11": "101588.71000",
                        "Hour12": "122617.03000",
                        "Hour13": "143125.42000",
                        "Hour14": "141081.15000",
                        "Hour15": "135561.20000",
                        "Hour16": "138648.03000",
                        "Hour17": "140430.45000",
                        "Hour18": "148884.04000",
                        "Hour19": "151310.44000",
                        "Hour20": "158149.85000",
                        "Hour21": "165265.01000",
                        "Hour22": "164478.71000",
                        "Hour23": "156818.92000",
                        "Hour24": "153420.74000"
                    }
                }
            ]
        },
        {
            "Date": "2023-03-21",
            "HourlyEntities": [
                {
                    "Id": "Sistema",
                    "Values": {
                        "code": "Sistema",
                        "Hour01": "142278.80000",
                        "Hour02": "143564.63000",
                        "Hour03": "143438.40000",
                        "Hour04": "137991.75000",
                        "Hour05": "126201.36000",
                        "Hour06": "126959.33000",
                        "Hour07": "117072.34000",
                        "Hour08": "111231.52000",
                        "Hour09": "110537.33000",
                        "Hour10": "119595.23000",
                        "Hour11": "131309.98000",
                        "Hour12": "140649.92000",
                        "Hour13": "148698.13000",
                        "Hour14": "162047.26000",
                        "Hour15": "175260.00000",
                        "Hour16": "182213.36000",
                        "Hour17": "175926.84000",
                        "Hour18": "158618.57000",
                        "Hour19": "148435.52000",
                        "Hour20": "157759.59000",
                        "Hour21": "159982.45000",
                        "Hour22": "149849.24000",
                        "Hour23": "133863.72000",
                        "Hour24": "139839.08000"
                    }
                }
            ]
        },
        {
            "Date": "2023-03-22",
            "HourlyEntities": [
                {
                    "Id": "Sistema",
                    "Values": {
                        "code": "Sistema",
                        "Hour01": "153218.37000",
                        "Hour02": "150573.80000",
                        "Hour03": "141731.53000",
                        "Hour04": "133118.18000",
                        "Hour05": "121348.68000",
                        "Hour06": "122580.02000",
                        "Hour07": "117688.83000",
                        "Hour08": "116945.58000",
                        "Hour09": "121314.30000",
                        "Hour10": "127783.01000",
                        "Hour11": "128147.63000",
                        "Hour12": "138356.74000",
                        "Hour13": "128612.65000",
                        "Hour14": "142584.49000",
                        "Hour15": "146000.81000",
                        "Hour16": "150857.18000",
                        "Hour17": "147259.67000",
                        "Hour18": "131495.86000",
                        "Hour19": "130005.04000",
                        "Hour20": "149313.87000",
                        "Hour21": "153691.91000",
                        "Hour22": "157526.09000",
                        "Hour23": "141277.31000",
                        "Hour24": "135116.87000"
                    }
                }
            ]
        },
        {
            "Date": "2023-03-23",
            "HourlyEntities": [
                {
                    "Id": "Sistema",
                    "Values": {
                        "code": "Sistema",
                        "Hour01": "142867.52000",
                        "Hour02": "143502.47000",
                        "Hour03": "139349.70000",
                        "Hour04": "134815.52000",
                        "Hour05": "134337.59000",
                        "Hour06": "139847.02000",
                        "Hour07": "129522.80000",
                        "Hour08": "123632.45000",
                        "Hour09": "120588.26000",
                        "Hour10": "123702.39000",
                        "Hour11": "128620.69000",
                        "Hour12": "139789.97000",
                        "Hour13": "141205.46000",
                        "Hour14": "146799.16000",
                        "Hour15": "149863.84000",
                        "Hour16": "154933.57000",
                        "Hour17": "154542.73000",
                        "Hour18": "155006.40000",
                        "Hour19": "143812.69000",
                        "Hour20": "148212.13000",
                        "Hour21": "153499.10000",
                        "Hour22": "162015.43000",
                        "Hour23": "150145.76000",
                        "Hour24": "142326.59000"
                    }
                }
            ]
        },
        {
            "Date": "2023-03-24",
            "HourlyEntities": [
                {
                    "Id": "Sistema",
                    "Values": {
                        "code": "Sistema",
                        "Hour01": "139390.85000",
                        "Hour02": "141415.23000",
                        "Hour03": "140243.43000",
                        "Hour04": "120610.93000",
                        "Hour05": "112978.83000",
                        "Hour06": "114630.28000",
                        "Hour07": "108053.56000",
                        "Hour08": "97325.65000",
                        "Hour09": "103396.46000",
                        "Hour10": "111460.84000",
                        "Hour11": "122560.69000",
                        "Hour12": "134946.06000",
                        "Hour13": "142573.76000",
                        "Hour14": "144951.47000",
                        "Hour15": "150236.29000",
                        "Hour16": "151232.36000",
                        "Hour17": "150103.94000",
                        "Hour18": "138381.00000",
                        "Hour19": "140491.98000",
                        "Hour20": "150419.70000",
                        "Hour21": "151623.89000",
                        "Hour22": "151418.26000",
                        "Hour23": "149972.89000",
                        "Hour24": "137176.30000"
                    }
                }
            ]
        },
        {
            "Date": "2023-03-25",
            "HourlyEntities": [
                {
                    "Id": "Sistema",
                    "Values": {
                        "code": "Sistema",
                        "Hour01": "152362.26000",
                        "Hour02": "145569.71000",
                        "Hour03": "140594.43000",
                        "Hour04": "126627.15000",
                        "Hour05": "120285.31000",
                        "Hour06": "124002.17000",
                        "Hour07": "107352.50000",
                        "Hour08": "107471.09000",
                        "Hour09": "116923.81000",
                        "Hour10": "118067.14000",
                        "Hour11": "118310.65000",
                        "Hour12": "123871.70000",
                        "Hour13": "124977.75000",
                        "Hour14": "134499.63000",
                        "Hour15": "128715.41000",
                        "Hour16": "131825.10000",
                        "Hour17": "128807.90000",
                        "Hour18": "135413.84000",
                        "Hour19": "153350.15000",
                        "Hour20": "146220.96000",
                        "Hour21": "148491.27000",
                        "Hour22": "163118.96000",
                        "Hour23": "161985.49000",
                        "Hour24": "147180.73000"
                    }
                }
            ]
        },
        {
            "Date": "2023-03-26",
            "HourlyEntities": [
                {
                    "Id": "Sistema",
                    "Values": {
                        "code": "Sistema",
                        "Hour01": "135113.85000",
                        "Hour02": "131872.74000",
                        "Hour03": "129479.00000",
                        "Hour04": "135299.00000",
                        "Hour05": "133170.43000",
                        "Hour06": "142743.77000",
                        "Hour07": "132112.91000",
                        "Hour08": "120204.50000",
                        "Hour09": "114594.80000",
                        "Hour10": "104756.29000",
                        "Hour11": "107752.45000",
                        "Hour12": "106330.78000",
                        "Hour13": "113289.72000",
                        "Hour14": "120890.33000",
                        "Hour15": "120926.10000",
                        "Hour16": "117837.25000",
                        "Hour17": "122067.35000",
                        "Hour18": "112148.85000",
                        "Hour19": "134724.95000",
                        "Hour20": "143833.05000",
                        "Hour21": "144465.44000",
                        "Hour22": "139443.48000",
                        "Hour23": "129435.36000",
                        "Hour24": "127083.44000"
                    }
                }
            ]
        },
        {
            "Date": "2023-03-27",
            "HourlyEntities": [
                {
                    "Id": "Sistema",
                    "Values": {
                        "code": "Sistema",
                        "Hour01": "117895.80000",
                        "Hour02": "125758.70000",
                        "Hour03": "119715.46000",
                        "Hour04": "111514.96000",
                        "Hour05": "103976.47000",
                        "Hour06": "114067.20000",
                        "Hour07": "113416.36000",
                        "Hour08": "104764.58000",
                        "Hour09": "98146.20000",
                        "Hour10": "110002.29000",
                        "Hour11": "110282.98000",
                        "Hour12": "128568.60000",
                        "Hour13": "121893.09000",
                        "Hour14": "124814.37000",
                        "Hour15": "134526.65000",
                        "Hour16": "141226.84000",
                        "Hour17": "131567.76000",
                        "Hour18": "129710.37000",
                        "Hour19": "142964.62000",
                        "Hour20": "155038.38000",
                        "Hour21": "158457.02000",
                        "Hour22": "149580.49000",
                        "Hour23": "145577.46000",
                        "Hour24": "145462.95000"
                    }
                }
            ]
        },
        {
            "Date": "2023-03-28",
            "HourlyEntities": [
                {
                    "Id": "Sistema",
                    "Values": {
                        "code": "Sistema",
                        "Hour01": "155555.27000",
                        "Hour02": "148426.76000",
                        "Hour03": "147637.49000",
                        "Hour04": "135742.98000",
                        "Hour05": "122495.34000",
                        "Hour06": "136285.37000",
                        "Hour07": "129574.02000",
                        "Hour08": "114538.40000",
                        "Hour09": "125647.22000",
                        "Hour10": "145407.55000",
                        "Hour11": "139108.48000",
                        "Hour12": "152345.25000",
                        "Hour13": "152440.14000",
                        "Hour14": "153503.40000",
                        "Hour15": "157130.80000",
                        "Hour16": "158685.99000",
                        "Hour17": "155467.59000",
                        "Hour18": "147095.13000",
                        "Hour19": "147711.17000",
                        "Hour20": "159712.06000",
                        "Hour21": "156947.30000",
                        "Hour22": "152465.24000",
                        "Hour23": "141933.05000",
                        "Hour24": "129541.57000"
                    }
                }
            ]
        },
        {
            "Date": "2023-03-29",
            "HourlyEntities": [
                {
                    "Id": "Sistema",
                    "Values": {
                        "code": "Sistema",
                        "Hour01": "141664.19000",
                        "Hour02": "142438.13000",
                        "Hour03": "131676.99000",
                        "Hour04": "125834.24000",
                        "Hour05": "123801.73000",
                        "Hour06": "177657.67000",
                        "Hour07": "191808.16000",
                        "Hour08": "123609.00000",
                        "Hour09": "177416.91000",
                        "Hour10": "197565.42000",
                        "Hour11": "198079.57000",
                        "Hour12": "211541.84000",
                        "Hour13": "207948.68000",
                        "Hour14": "205646.95000",
                        "Hour15": "211991.09000",
                        "Hour16": "220552.08000",
                        "Hour17": "215032.38000",
                        "Hour18": "221282.97000",
                        "Hour19": "230266.63000",
                        "Hour20": "233915.84000",
                        "Hour21": "227293.70000",
                        "Hour22": "225347.06000",
                        "Hour23": "205375.98000",
                        "Hour24": "185026.50000"
                    }
                }
            ]
        },
        {
            "Date": "2023-03-30",
            "HourlyEntities": [
                {
                    "Id": "Sistema",
                    "Values": {
                        "code": "Sistema",
                        "Hour01": "188952.21000",
                        "Hour02": "191575.74000",
                        "Hour03": "180995.19000",
                        "Hour04": "182074.64000",
                        "Hour05": "192991.78000",
                        "Hour06": "202620.13000",
                        "Hour07": "203990.86000",
                        "Hour08": "203212.67000",
                        "Hour09": "216583.25000",
                        "Hour10": "230539.31000",
                        "Hour11": "227743.95000",
                        "Hour12": "153755.09000",
                        "Hour13": "250418.12000",
                        "Hour14": "246721.33000",
                        "Hour15": "241700.25000",
                        "Hour16": "238893.47000",
                        "Hour17": "239172.80000",
                        "Hour18": "223469.63000",
                        "Hour19": "237606.93000",
                        "Hour20": "239821.09000",
                        "Hour21": "241361.57000",
                        "Hour22": "233699.88000",
                        "Hour23": "209666.92000",
                        "Hour24": "190759.01000"
                    }
                }
            ]
        },
        {
            "Date": "2023-03-31",
            "HourlyEntities": [
                {
                    "Id": "Sistema",
                    "Values": {
                        "code": "Sistema",
                        "Hour01": "187401.54000",
                        "Hour02": "180930.21000",
                        "Hour03": "186108.70000",
                        "Hour04": "174107.24000",
                        "Hour05": "174121.75000",
                        "Hour06": "187745.05000",
                        "Hour07": "181456.14000",
                        "Hour08": "180364.36000",
                        "Hour09": "187406.02000",
                        "Hour10": "200261.51000",
                        "Hour11": "206446.24000",
                        "Hour12": "221081.98000",
                        "Hour13": "221651.90000",
                        "Hour14": "225295.82000",
                        "Hour15": "220249.22000",
                        "Hour16": "223443.52000",
                        "Hour17": "175423.64000",
                        "Hour18": "132833.32000",
                        "Hour19": "222730.49000",
                        "Hour20": "239269.74000",
                        "Hour21": "239075.15000",
                        "Hour22": "221728.85000",
                        "Hour23": "210012.91000",
                        "Hour24": "200177.30000"
                    }
                }
            ]
        },
        {
            "Date": "2023-04-01",
            "HourlyEntities": [
                {
                    "Id": "Sistema",
                    "Values": {
                        "code": "Sistema",
                        "Hour01": "157267.74000",
                        "Hour02": "164291.17000",
                        "Hour03": "166949.66000",
                        "Hour04": "152834.34000",
                        "Hour05": "148208.63000",
                        "Hour06": "143209.09000",
                        "Hour07": "134356.33000",
                        "Hour08": "134661.55000",
                        "Hour09": "128433.05000",
                        "Hour10": "122741.72000",
                        "Hour11": "130729.95000",
                        "Hour12": "136392.95000",
                        "Hour13": "145214.65000",
                        "Hour14": "140411.82000",
                        "Hour15": "144318.95000",
                        "Hour16": "145035.05000",
                        "Hour17": "143369.19000",
                        "Hour18": "141907.09000",
                        "Hour19": "151702.13000",
                        "Hour20": "153765.93000",
                        "Hour21": "155459.53000",
                        "Hour22": "167196.07000",
                        "Hour23": "167896.34000",
                        "Hour24": "153658.21000"
                    }
                }
            ]
        },
        {
            "Date": "2023-04-02",
            "HourlyEntities": [
                {
                    "Id": "Sistema",
                    "Values": {
                        "code": "Sistema",
                        "Hour01": "145655.35000",
                        "Hour02": "138433.47000",
                        "Hour03": "138816.05000",
                        "Hour04": "148002.86000",
                        "Hour05": "147314.78000",
                        "Hour06": "143799.21000",
                        "Hour07": "133998.99000",
                        "Hour08": "132074.92000",
                        "Hour09": "120832.00000",
                        "Hour10": "121228.71000",
                        "Hour11": "117854.01000",
                        "Hour12": "118903.10000",
                        "Hour13": "121549.04000",
                        "Hour14": "125173.28000",
                        "Hour15": "115517.94000",
                        "Hour16": "110692.44000",
                        "Hour17": "106080.80000",
                        "Hour18": "102251.19000",
                        "Hour19": "117224.66000",
                        "Hour20": "130121.69000",
                        "Hour21": "136411.78000",
                        "Hour22": "135967.54000",
                        "Hour23": "133541.55000",
                        "Hour24": "118112.54000"
                    }
                }
            ]
        },
        {
            "Date": "2023-04-03",
            "HourlyEntities": [
                {
                    "Id": "Sistema",
                    "Values": {
                        "code": "Sistema",
                        "Hour01": "142643.96000",
                        "Hour02": "142009.65000",
                        "Hour03": "145141.45000",
                        "Hour04": "136130.63000",
                        "Hour05": "122972.99000",
                        "Hour06": "123491.37000",
                        "Hour07": "117788.37000",
                        "Hour08": "121251.30000",
                        "Hour09": "139544.92000",
                        "Hour10": "141169.20000",
                        "Hour11": "146628.14000",
                        "Hour12": "148658.84000",
                        "Hour13": "150555.08000",
                        "Hour14": "155817.66000",
                        "Hour15": "154479.39000",
                        "Hour16": "176414.32000",
                        "Hour17": "158670.86000",
                        "Hour18": "147200.88000",
                        "Hour19": "156197.40000",
                        "Hour20": "161555.41000",
                        "Hour21": "159289.09000",
                        "Hour22": "158690.24000",
                        "Hour23": "152799.11000",
                        "Hour24": "162926.39000"
                    }
                }
            ]
        }
    ]
}